nanoflow-0.10.0.dist-info/METADATA
nanoflow-0.10.0.dist-info/WHEEL
nanoflow-0.10.0.dist-info/entry_points.txt
nanoflow-0.10.0.dist-info/licenses/LICENCE
nanoflow/__init__.py
nanoflow/__main__.py
nanoflow/__version__.py
nanoflow/cli.py
nanoflow/config.py
nanoflow/executor.py
nanoflow/resource_pool.py
nanoflow/task.py
nanoflow/tui.py
nanoflow/utils.py
nanoflow/workflow.py
nanoflow-0.10.0.dist-info/RECORD
