Metadata-Version: 2.1
Name: nanoflow
Version: 0.10.0
Summary: A simple and efficient workflow framework for Python
Author-Email: Zhan Rongrui <2742392377@qq.com>
License: GPL-3.0
Classifier: Environment :: Console
Classifier: Operating System :: OS Independent
Classifier: License :: OSI Approved :: GNU General Public License v3 (GPLv3)
Classifier: Typing :: Typed
Classifier: Programming Language :: Python
Classifier: Programming Language :: Python :: 3
Classifier: Programming Language :: Python :: 3.12
Classifier: Programming Language :: Python :: 3.13
Classifier: Programming Language :: Python :: Implementation :: CPython
Project-URL: Homepage, https://github.com/zrr1999/nanoflow.git
Project-URL: Repository, https://github.com/zrr1999/nanoflow.git
Requires-Python: >=3.12
Requires-Dist: loguru>=0.7.0
Requires-Dist: networkx>=3.0
Requires-Dist: pydantic>=2.0.0
Requires-Dist: toml>=0.10.0
Requires-Dist: rich>=13.8.0
Requires-Dist: typer>=0.12.5
Requires-Dist: textual>=0.81.0
Requires-Dist: humanize>=4.11.0
Provides-Extra: server
Requires-Dist: fastapi>=0.115.0; extra == "server"
Requires-Dist: uvicorn>=0.30.6; extra == "server"
Provides-Extra: plot
Requires-Dist: matplotlib>=3.9.0; extra == "plot"
